{
  "file_name": "workers.md",
  "id": "workers",
  "file_dir": "/",
  "title": "Workers",
  "sidebar_label": "Workers",
  "description": "This guide provides a comprehensive overview of Temporal Workers.",
  "use_description": true,
  "toc_max_heading_level": 4,
  "add_tabs_support": true,
  "sections": [
    {
      "type": "p",
      "id": "concepts/what-is-a-worker"
    },
    {
      "type": "h2",
      "id": "concepts/what-is-a-worker-program"
    },
    {
      "type": "h2",
      "id": "concepts/what-is-a-worker-entity"
    },
    {
      "type": "h2",
      "id": "concepts/what-is-a-worker-process"
    }
  ]
}
