{
    "file_name": "support.md",
    "id": "support",
    "slug": "/cloud/support",
    "file_dir": "production-deployment/cloud/introduction",
    "title": "Services, support, and training - Temporal Cloud",
    "sidebar_label": "Support",
    "sidebar_position": 7,
    "description": "Temporal Cloud users can reach out for help through our community Slack channel, or file a support ticket through Zendesk. ",
    "use_description": false,
    "toc_max_heading_level": 4,
    "add_tabs_support": false,
    "sections": [
        {
            "type": "p",
            "id": "cloud/support-intro"
        },
        {
            "type": "h2",
            "id": "cloud/support-service-guarantees"
        },
        {
            "type": "h2",
            "id": "cloud/support-support-guarantees"
        },
        {
            "type": "h2",
            "id": "cloud/support-create-ticket"
        },
        {
            "type": "h2",
            "id": "cloud/support-developer-resources"
        }
    ]
}